<?xml version="1.0" encoding="utf-8" ?>
<dwsync>
<file name="CryoCellLogo.png" server="rbadesign.us/public_html/" local="130275707504836835" remote="130350798000000000" Dst="0" />
<file name="media-playback-start-4.png" server="rbadesign.us/public_html/" local="130275707505006855" remote="130350798000000000" Dst="0" />
<file name="media-playback-start-6.png" server="rbadesign.us/public_html/" local="130275707505036860" remote="130350798000000000" Dst="0" />
<file name="media-playback-stop-4.png" server="rbadesign.us/public_html/" local="130275707505046857" remote="130350798000000000" Dst="0" />
<file name="media-playback-pause-4.png" server="rbadesign.us/public_html/" local="130275707505006855" remote="130350798000000000" Dst="0" />
<file name="media-seek-backward-4.png" server="rbadesign.us/public_html/" local="130275707505056867" remote="130350798000000000" Dst="0" />
<file name="media-seek-forward-4.png" server="rbadesign.us/public_html/" local="130275707505056867" remote="130350798000000000" Dst="0" />
<file name="media-skip-backward-4.png" server="rbadesign.us/public_html/" local="130275707505066865" remote="130350798000000000" Dst="0" />
<file name="loadingbig.gif" server="rbadesign.us/public_html/" local="130275707504996855" remote="130350798000000000" Dst="0" />
<file name="media-skip-forward-4.png" server="rbadesign.us/public_html/" local="130275707505066865" remote="130350798000000000" Dst="0" />
<file name="view-refresh.png" server="rbadesign.us/public_html/" local="130275707505476913" remote="130350798600000000" Dst="0" />
<file name="go-home-4.png" server="rbadesign.us/public_html/" local="130275707504966850" remote="130350798000000000" Dst="0" />
<file name="background.jpg" server="rbadesign.us/public_html/" local="130275707504926842" remote="130350798000000000" Dst="0" />
<file name="button.png" server="rbadesign.us/public_html/" local="130275707504946849" remote="130350798000000000" Dst="0" />
<file name="media-playback-start.png" server="rbadesign.us/public_html/" local="130275707505036860" remote="130350798000000000" Dst="0" />
<file name="button-2302.png" server="rbadesign.us/public_html/" local="130275707504936849" remote="130350798000000000" Dst="0" />
<file name="button-small.png" server="rbadesign.us/public_html/" local="130275707504946849" remote="130350798000000000" Dst="0" />
<file name="button_blue_repeat.png" server="rbadesign.us/public_html/" local="130275707504956850" remote="130350798000000000" Dst="0" />
<file name="go-next-7.png" server="rbadesign.us/public_html/" local="130275707504976848" remote="130350798000000000" Dst="0" />
<file name="go-next-view.png" server="rbadesign.us/public_html/" local="130275707504976848" remote="130350798000000000" Dst="0" />
<file name="go-previous-7.png" server="rbadesign.us/public_html/" local="130275707504986858" remote="130350798000000000" Dst="0" />
<file name="desktop-alert-icon-32x32.png" server="rbadesign.us/public_html/" local="130275707504966850" remote="130350798000000000" Dst="0" />
<file name="up-arrow.png" server="rbadesign.us/public_html/" local="130275707505466912" remote="130350798600000000" Dst="0" />
</dwsync>